{
  "type": "FeatureCollection",
  "features": [
    {
      "type": "Feature",
      "geometry": {
        "type": "Point",
        "coordinates": [
          -85.6339173752,
          34.3989183472
        ]
      },
      "properties": {
        "name": "Little River Canyon National Preserve, the Trail of Tears",
        "notes": "Little River Canyon National Preserve, the Trail of Tears\nhttps://www.nps.gov/places/little-river-canyon-national-preserve-trail-of-tears.htm\n\n<p>Little River Canyon National Preserve is a place of beauty that is also host to stories of adversity and survival. Over 1,100 men, women, and children moved through the Little River area during the removal of the Cherokee and Muscogee (Creek) Indians. Cherokee John Benge led the Fort Payne group of American Indians over 798 miles on the Trail of Tears to Indian Territory in what is now Oklahoma, crossing the Little River above the falls near the present-day Highway 35 bridge.</p> <h2>Site Information</h2> <p><strong>Location</strong> (4322 Little River Trail NE (472 AL Hwy 35 for GPS))<br /> <br /> <strong>Access </strong><br /> Contact visitor center hours and directions to the river crossing site</p> <p><em><a href=\"https://www.nps.gov/trte/planyourvisit/safety.htm\">Safety Considerations</a></em></p> <h3><a href=\"https://www.nps.gov/liri/index.htm\">More Site Information</a></h3> <h2><a href=\"https://www.nps.gov/trte/index.htm\">Trail of Tears National Historic Trail</a></h2>",
        "icon": "red-pin-down.png"
      }
    }
  ]
}